stellrent_auth/__init__.py
stellrent_auth/auth.py
stellrent_auth/http_auth_basic.py
stellrent_auth-0.0.6.dist-info/LICENSE
stellrent_auth-0.0.6.dist-info/METADATA
stellrent_auth-0.0.6.dist-info/WHEEL
stellrent_auth-0.0.6.dist-info/top_level.txt
stellrent_auth-0.0.6.dist-info/RECORD
