Metadata-Version: 2.1
Name: stellrent-auth
Version: 0.0.6
Summary: Authentications Methods: Basic Auth, OAUTH2 and OpenID standards
Author: Marcus R. Magalhães
Author-email: Marcus Rodrigues Magalhães <marcusrodrigues.magalhaes@stellantis.com>
Project-URL: Homepage, https://github.com/stellrent/stellrent-auth
Project-URL: Issues, https://github.com/stellrent/stellrent-auth/issues
Classifier: Development Status :: 4 - Beta
Classifier: Programming Language :: Python :: 3
Classifier: Programming Language :: Python :: 3.11
Classifier: License :: OSI Approved :: MIT License
Classifier: Operating System :: OS Independent
Classifier: Framework :: Pytest
Classifier: Topic :: Software Development :: Libraries :: Python Modules
Requires-Python: >=3.11
License-File: LICENSE
Requires-Dist: pip ==24.0
Requires-Dist: flask ==2.3.3
Requires-Dist: pyjwt ==2.8.0
Requires-Dist: requests-oauthlib ==1.3.1
Requires-Dist: oauthlib ==3.2.2
Requires-Dist: stellrent-response ==0.0.6
Requires-Dist: cryptography ==42.0.5
Requires-Dist: Flask-HTTPAuth ==4.8.0
Requires-Dist: python-decouple ==3.8
